lppa/__init__.py
lppa/__main__.py
lppa/auth.py
lppa/cli.py
lppa/constants.py
lppa/ppa.py
lppa/processors.py
lppa/utils.py
lppa-0.3.0.dist-info/LICENSE
lppa-0.3.0.dist-info/METADATA
lppa-0.3.0.dist-info/WHEEL
lppa-0.3.0.dist-info/entry_points.txt
lppa-0.3.0.dist-info/top_level.txt
lppa-0.3.0.dist-info/RECORD
