Metadata-Version: 2.1
Name: lppa
Version: 0.3.0
Summary: Request PPAs for deb source packages
Home-page: https://github.com/athos-ribeiro/lppa
Author: Athos Ribeiro
Author-email: athos.ribeiro@canonical.com
License: GPLv3+
Project-URL: Changelog, https://github.com/athos-ribeiro/lppa/blob/main/CHANGELOG.md
Project-URL: Bug Tracker, https://github.com/athos-ribeiro/lppa/issues
Project-URL: Source Code, https://github.com/athos-ribeiro/lppa
Keywords: PPA,Ubuntu,Launchpad
Platform: any
Classifier: Development Status :: 4 - Beta
Classifier: Intended Audience :: Developers
Classifier: License :: OSI Approved :: GNU General Public License v3 or later (GPLv3+)
Classifier: Programming Language :: Python :: 3
Classifier: Programming Language :: Python :: 3.8
Classifier: Programming Language :: Python :: 3.9
Classifier: Programming Language :: Python :: 3.10
Classifier: Programming Language :: Python :: 3.11
Classifier: Programming Language :: Python :: 3.12
Classifier: Programming Language :: Python :: 3 :: Only
Requires-Python: >=3.6
License-File: LICENSE
Requires-Dist: launchpadlib
Requires-Dist: requests
